wagtail_json_widget/__init__.py
wagtail_json_widget/apps.py
wagtail_json_widget/blocks.py
wagtail_json_widget/models.py
wagtail_json_widget/widgets.py
wagtail_json_widget/__pycache__/__init__.cpython-311.pyc
wagtail_json_widget/__pycache__/__init__.cpython-312.pyc
wagtail_json_widget/__pycache__/__init__.cpython-39.pyc
wagtail_json_widget/static/dist/jsoneditor.9.7.4.min.css
wagtail_json_widget/static/dist/jsoneditor.9.7.4.min.js
wagtail_json_widget/static/dist/img/jsoneditor-icons.svg
wagtail_json_widget/static/wagtail_json_widget/css/json_widget.css
wagtail_json_widget/static/wagtail_json_widget/js/json_block_widget.js
wagtail_json_widget/static/wagtail_json_widget/js/json_widget.js
wagtail_json_widget/templates/wagtail_json_widget.html
wagtail_json_widget-0.0.9.dist-info/licenses/LICENSE
wagtail_json_widget-0.0.9.dist-info/METADATA
wagtail_json_widget-0.0.9.dist-info/WHEEL
wagtail_json_widget-0.0.9.dist-info/top_level.txt
wagtail_json_widget-0.0.9.dist-info/RECORD
