Metadata-Version: 2.4
Name: wagtail_json_widget
Version: 0.0.9
Summary: JSONEditor for Wagtail CMS
Home-page: https://github.com/cursive-works/wagtail-json-widget
Author: Patrick Smith
Author-email: pat.smith@cursive.works
License: MIT
Keywords: WAGTAIL,JSON,STREAMFIELD,JSONEditor,WAGTAIL CMS
Classifier: Development Status :: 4 - Beta
Classifier: Environment :: Web Environment
Classifier: Framework :: Django
Classifier: Intended Audience :: Developers
Classifier: Operating System :: OS Independent
Classifier: Programming Language :: Python
Classifier: Programming Language :: Python :: 3.7
Classifier: Programming Language :: Python :: 3.8
Classifier: Programming Language :: Python :: 3.9
Classifier: Programming Language :: Python :: 3.10
Classifier: Programming Language :: Python :: 3.11
Classifier: Topic :: Internet :: WWW/HTTP
Classifier: Topic :: Internet :: WWW/HTTP :: Dynamic Content
Classifier: Topic :: Software Development
License-File: LICENSE
Requires-Dist: wagtail>=4.0
Dynamic: author
Dynamic: author-email
Dynamic: classifier
Dynamic: description
Dynamic: description-content-type
Dynamic: home-page
Dynamic: keywords
Dynamic: license
Dynamic: license-file
Dynamic: requires-dist
Dynamic: summary
